senselyClient/__init__.py
senselyClient/senselyClient.py
senselyClient-0.0.12.dist-info/METADATA
senselyClient-0.0.12.dist-info/WHEEL
senselyClient-0.0.12.dist-info/top_level.txt
senselyClient-0.0.12.dist-info/RECORD
