Metadata-Version: 2.1
Name: senselyClient
Version: 0.0.12
Summary: A library to send data stream for ingestion and analytics
Home-page: https://github.com/readall/senselyClient
Author: Sensely.in
Author-email: mail@sensely.in
License: UNKNOWN
Platform: UNKNOWN
Classifier: Programming Language :: Python :: 3
Classifier: Operating System :: OS Independent
